trainviz/__init__.py
trainviz/app.py
trainviz/server.py
trainviz/state.py
trainviz/web/dashboard.js
trainviz/web/index.html
trainviz/web/styles.css
trainviz-0.1.0.dist-info/licenses/LICENSE.txt
trainviz-0.1.0.dist-info/METADATA
trainviz-0.1.0.dist-info/WHEEL
trainviz-0.1.0.dist-info/entry_points.txt
trainviz-0.1.0.dist-info/top_level.txt
trainviz-0.1.0.dist-info/RECORD
